Metadata-Version: 1.0
Name: seswatcher
Version: 0.2
Summary: A small tool to prevent AWS SES from blocked by exceeding Bounces Rate or Complaints Rate
Home-page: https://github.com/khanhicetea/seswatcher
Author: KhanhIceTea
Author-email: khanhicetea@gmail.com
License: UNKNOWN
Keywords: ses,aws
Platform: UNKNOWN
